vagoncli/__init__.py
vagoncli/constants.py
vagoncli/helpers.py
vagoncli/commands/__init__.py
vagoncli/commands/application_version.py
vagoncli/commands/configure.py
vagoncli/commands/create_application.py
vagoncli/commands/machine_types.py
vagon_cli-0.0.4.dist-info/METADATA
vagon_cli-0.0.4.dist-info/WHEEL
vagon_cli-0.0.4.dist-info/entry_points.txt
vagon_cli-0.0.4.dist-info/top_level.txt
vagon_cli-0.0.4.dist-info/RECORD
