Metadata-Version: 2.4
Name: vagon-cli
Version: 0.0.4
Summary: Vagon CLI for managing Vagon Streams resources
Author: Vagon, Inc.
Author-email: info@vagon.io
Requires-Dist: click
Requires-Dist: requests
Dynamic: author
Dynamic: author-email
Dynamic: requires-dist
Dynamic: summary
